usbrply/__init__.py
usbrply/com_pcap.py
usbrply/commenter.py
usbrply/cprinter.py
usbrply/device_filter.py
usbrply/filters.py
usbrply/lin_pcap.py
usbrply/parsers.py
usbrply/pcap_util.py
usbrply/printer.py
usbrply/printers.py
usbrply/pyprinter.py
usbrply/setup_filter.py
usbrply/usb.py
usbrply/util.py
usbrply/vidpid_filter.py
usbrply/win_pcap.py
usbrply/serial/__init__.py
usbrply/serial/mpsse.py
usbrply/serial/parsers.py
usbrply/serial/printers.py
usbrply/serial/serial.py
usbrply-2.1.1.data/scripts/usbrply
usbrply-2.1.1.dist-info/COPYING.txt
usbrply-2.1.1.dist-info/METADATA
usbrply-2.1.1.dist-info/WHEEL
usbrply-2.1.1.dist-info/top_level.txt
usbrply-2.1.1.dist-info/RECORD
