Metadata-Version: 2.1
Name: usbrply
Version: 2.1.1
Summary: Replay captured USB packets from .pcap file.
Home-page: https://github.com/JohnDMcMaster/usbrply
Author: John McMaster
Author-email: JohnDMcMaster@gmail.com
License: BSD
Keywords: libusb pcap
Platform: UNKNOWN
Classifier: License :: OSI Approved :: BSD License
Requires-Dist: python-pcapng
